{
    "id": "bundle--cdaa2562-f061-4d04-a881-ea7454ec261b",
    "spec_version": "2.0",
    "objects": [
        {
            "name": "sdf",
            "identity_class": "events",
            "type": "identity",
            "id": "identity--6e4a33d1-8af6-43ef-9997-b4e2dfc29b1d",
            "created": "2020-07-04T22:02:24.800Z",
            "modified": "2020-07-04T22:02:24.800Z"
        },
        {
            "id": "observed-data--89ac44f0-0a3e-42d2-bbf5-569c92b5060d",
            "number_observed": 1,
            "first_observed": "2020-07-06T14:10:15.143103Z",
            "last_observed": "2020-07-06T14:10:15.143103Z",
            "created": "2020-07-06T14:10:15.143Z",
            "modified": "2020-07-06T14:10:15.143Z",
            "objects": {
                "0": {
                    "value": "192.168.1.12",
                    "type": "ipv4-addr"
                },
                "1": {
                    "value": "olfe.ag",
                    "type": "domain-name"
                },
                "2": {
                    "value": "CC:46:D6:0d:0b:c3",
                    "type": "mac-addr"
                },
                "3": {
                    "value": "http://eshuffl-dubli-tempter.comcast/5tek8ToBYaCw/ocatin-exhilaratio-interspers.rar",
                    "type": "url"
                },
                "4": {
                    "user_id": "acteri-give-philanthropi",
                    "type": "user-account"
                },
                "5": {
                    "name": "conographica-balde-jadedl.bcm",
                    "hashes": {
                        "TLSH": "e2fCE6A7Eecc00c88cde2FA117CEACb7cc1bea79e2cc2FcbEebCAce32ac941FB4beC4b"
                    },
                    "type": "file"
                }
            },
            "type": "observed-data"
        },
        {
            "id": "observed-data--0a88da74-82ea-46da-a431-ad285a333726",
            "number_observed": 1,
            "first_observed": "2020-07-09T17:38:38.049523Z",
            "last_observed": "2020-07-09T17:38:38.049523Z",
            "created": "2020-07-09T17:38:38.049Z",
            "modified": "2020-07-09T17:38:38.049Z",
            "objects": {
                "0": {
                    "value": "192.168.1.29",
                    "type": "ipv4-addr"
                },
                "1": {
                    "value": "umpstartin.gh",
                    "type": "domain-name"
                },
                "2": {
                    "value": "CC:46:D6:36:33:da",
                    "type": "mac-addr"
                },
                "3": {
                    "value": "https://addler.yachts/UiU2y281R5id778lZ/0n5OH2ygPK6D86B/alutin-tidie.cbf",
                    "type": "url"
                },
                "4": {
                    "user_id": "ollinator-skippe",
                    "type": "user-account"
                },
                "5": {
                    "name": "uill-mathematic.ipa",
                    "hashes": {
                        "TLSH": "260BF42f2386fa35C4C54eC2dfC9B5Da7D1c323cBc5Dd3Bde9FdC96c22Ea5A7dDFB47f"
                    },
                    "type": "file"
                }
            },
            "type": "observed-data"
        },
        {
            "id": "observed-data--2843c997-5291-4b38-9eb1-63f65b2fb74d",
            "number_observed": 1,
            "first_observed": "2020-07-07T17:04:38.501292Z",
            "last_observed": "2020-07-07T17:04:38.501292Z",
            "created": "2020-07-07T17:04:38.501Z",
            "modified": "2020-07-07T17:04:38.501Z",
            "objects": {
                "0": {
                    "value": "192.168.1.99",
                    "type": "ipv4-addr"
                },
                "1": {
                    "value": "escriptiv-mine-whack.caseih",
                    "type": "domain-name"
                },
                "2": {
                    "value": "CC:46:D6:59:b5:60",
                    "type": "mac-addr"
                },
                "3": {
                    "value": "https://eurotic.art/W9NEwLy43/RaNDl6j64/NSMrgwc667M/lbu-oxtai-hygienicall.txd",
                    "type": "url"
                },
                "4": {
                    "user_id": "rchivis-legerdemai",
                    "type": "user-account"
                },
                "5": {
                    "name": "ouple.red",
                    "hashes": {
                        "SHA3-384": "A7c08F9A23dfCfeaa37CcE5dC8D58C025FE9cC0AfaeEE05e36aBd9f0265FbD0931Eb027d2cc63ebe15cD69d7c7e8Df75"
                    },
                    "type": "file"
                }
            },
            "type": "observed-data"
        },
        {
            "id": "observed-data--bf348c88-68e1-4010-b5a0-2a86982b7c7f",
            "number_observed": 1,
            "first_observed": "2020-07-21T22:34:28.664614Z",
            "last_observed": "2020-07-21T22:34:28.664614Z",
            "created": "2020-07-21T22:34:28.664Z",
            "modified": "2020-07-21T22:34:28.664Z",
            "objects": {
                "0": {
                    "value": "192.168.1.36",
                    "type": "ipv4-addr"
                },
                "1": {
                    "value": "cu-personifyin.abb",
                    "type": "domain-name"
                },
                "2": {
                    "value": "CC:46:D6:a0:63:10",
                    "type": "mac-addr"
                },
                "3": {
                    "value": "https://ramline-unicycl.holiday/DJdYm4z737of/EWc9jL4Hdm7c96oT/rAE/utation-alrigh-antechambe.ffa",
                    "type": "url"
                },
                "4": {
                    "user_id": "nsea",
                    "type": "user-account"
                },
                "5": {
                    "name": "nvo-char.db2",
                    "hashes": {
                        "SHA3-256": "aC164dc3BAc1F03fcd19Ae2fCA3dD15a732f6Dcad3F18d3eBBeeFa60Da6cc5cd"
                    },
                    "type": "file"
                }
            },
            "type": "observed-data"
        },
        {
            "id": "observed-data--e73e86e0-3f98-4498-97fe-30769c7fa4a4",
            "number_observed": 1,
            "first_observed": "2020-07-14T10:14:11.952492Z",
            "last_observed": "2020-07-14T10:14:11.952492Z",
            "created": "2020-07-14T10:14:11.952Z",
            "modified": "2020-07-14T10:14:11.952Z",
            "objects": {
                "0": {
                    "value": "192.168.1.230",
                    "type": "ipv4-addr"
                },
                "1": {
                    "value": "nfuriate-aerobic-bribe.pa",
                    "type": "domain-name"
                },
                "2": {
                    "value": "CC:46:D6:35:99:0c",
                    "type": "mac-addr"
                },
                "3": {
                    "value": "https://cuttle-trinida-uncreate.sm/n0IGV3noUZkERK6SU/uTI5FG0xsz8OQ3/hoddil-multifariou.qbr",
                    "type": "url"
                },
                "4": {
                    "user_id": "elineatio",
                    "type": "user-account"
                },
                "5": {
                    "name": "onkey-abjectl.qdat",
                    "hashes": {
                        "SHA3-224": "BFF6725d98aB554463cAc5BeF130A404b893eEb436a931bD34AE4e0e"
                    },
                    "type": "file"
                }
            },
            "type": "observed-data"
        }
    ],
    "type": "bundle"
}